CHANGELOG.md
LICENSE.md
README.md
setup.py
bspline/__init__.py
bspline/bspline.py
bspline/splinelab.py
bspline.egg-info/PKG-INFO
bspline.egg-info/SOURCES.txt
bspline.egg-info/dependency_links.txt
bspline.egg-info/requires.txt
bspline.egg-info/top_level.txt
bspline.egg-info/zip-safe
test/bspline.test.ipynb
test/demo.py